raglab/__init__.py
raglab/chunk/__init__.py
raglab/chunk/regex_text_chunker.py
raglab/embeddings/__init__.py
raglab/embeddings/azure_openai.py
raglab/embeddings/base.py
raglab/embeddings/openai.py
raglab/graphrag/__init__.py
raglab/graphrag/data_contracts/__init__.py
raglab/graphrag/data_contracts/graph.py
raglab/graphrag/data_contracts/type.py
raglab/graphrag/prompt/__init__.py
raglab/graphrag/prompt/chunk_graph_extraction.py
raglab/graphrag/prompt/community.py
raglab/graphrag/prompt/disambiguation.py
raglab/graphrag/prompt/expert.py
raglab/graphrag/prompt/language.py
raglab/graphrag/prompt/search.py
raglab/graphrag/prompt_functions/__init__.py
raglab/graphrag/prompt_functions/chunk_graph_extraction.py
raglab/graphrag/prompt_functions/community.py
raglab/graphrag/prompt_functions/disambiguation.py
raglab/graphrag/prompt_functions/expert.py
raglab/graphrag/prompt_functions/language.py
raglab/graphrag/search_functions/__init__.py
raglab/graphrag/search_functions/example.py
raglab/graphrag/utils/__init__.py
raglab/graphrag/utils/communities.py
raglab/graphrag/utils/dataclass_utils.py
raglab/graphrag/utils/graph_file_loader.py
raglab/graphrag/utils/graph_network_x_utils.py
raglab/graphrag/utils/graph_utils.py
raglab/graphrag/visual/__init__.py
raglab/graphrag/visual/echart.py
raglab/graphrag/visual/network_x.py
raglab/llms/__init__.py
raglab/llms/azure_openai.py
raglab/llms/base.py
raglab/llms/huggingface_llm.py
raglab/llms/openai.py
raglab/utils/__init__.py
raglab/utils/json_paser.py
raglab/utils/parallel_utils.py
raglab2-0.2.4.dist-info/LICENSE
raglab2-0.2.4.dist-info/METADATA
raglab2-0.2.4.dist-info/WHEEL
raglab2-0.2.4.dist-info/top_level.txt
raglab2-0.2.4.dist-info/RECORD
