Metadata-Version: 2.1
Name: raglab2
Version: 0.2.4
Summary: RAG-LAB is an open-source lighter, faster and cheaper RAG toolkit supported by Target Pilot, designed to transform the latest RAG concepts into stable and practical engineering tools. The project currently supports GraphRAG and HybridRAG.
Home-page: https://github.com/EcomPilot/rag-lab
Author: targetpilot
Author-email: ai-research@targetpilot.ai
License: MIT
Classifier: Programming Language :: Python :: 3
Classifier: License :: OSI Approved :: Apache Software License
Classifier: Operating System :: OS Independent
License-File: LICENSE
Requires-Dist: openai
Requires-Dist: requests
Requires-Dist: numpy
Requires-Dist: pyecharts
Requires-Dist: matplotlib
Requires-Dist: networkx
Requires-Dist: pandas
Requires-Dist: loguru
Requires-Dist: regex
Requires-Dist: tqdm
